reptimer/__init__.py
reptimer/commandline.py
reptimer/doc.txt
reptimer/main.py
reptimer/test.py
reptimer-0.0.2.dist-info/LICENSE.txt
reptimer-0.0.2.dist-info/METADATA
reptimer-0.0.2.dist-info/WHEEL
reptimer-0.0.2.dist-info/entry_points.txt
reptimer-0.0.2.dist-info/top_level.txt
reptimer-0.0.2.dist-info/RECORD
